synecure/__init__.py
synecure/bsync.py
synecure/cli.py
synecure/gitignore_parser.py
synecure/utils.py
synecure/version.py
synecure-0.2.1.dist-info/entry_points.txt
synecure-0.2.1.dist-info/WHEEL
synecure-0.2.1.dist-info/METADATA
synecure-0.2.1.dist-info/RECORD
