Metadata-Version: 2.1
Name: synecure
Version: 0.2.1
Summary: File sync utility
Home-page: https://github.com/breuleux/synecure
License: GPL-3.0-or-later
Author: Olivier Breuleux
Author-email: breuleux@gmail.com
Requires-Python: >=3.7,<4.0
Classifier: License :: OSI Approved :: GNU General Public License v3 or later (GPLv3+)
Classifier: Programming Language :: Python :: 3
Classifier: Programming Language :: Python :: 3.7
Classifier: Programming Language :: Python :: 3.8
Classifier: Programming Language :: Python :: 3.9
Requires-Dist: coleo (>=0.2.1,<0.3.0)
Project-URL: Repository, https://github.com/breuleux/synecure
